<?xml version="1.0"?>
<!DOCTYPE hibernate-mapping PUBLIC "-//Hibernate/Hibernate Mapping DTD 3.0//EN"
"http://hibernate.sourceforge.net/hibernate-mapping-3.0.dtd">
<!-- Generated 19/03/2013 2:31:28 AM by Hibernate Tools 3.2.1.GA -->
<hibernate-mapping>
    <class name="entity.common.Address" table="address" catalog="qbits_erp">
        <id name="personId" type="int">
            <column name="person_id" />
            <generator class="foreign">
                <param name="property">person</param>
            </generator>
        </id>
        <property name="address" type="string">
            <column name="address" length="200" not-null="true" />
        </property>
        <property name="city" type="string">
            <column name="city" length="50" not-null="true" />
        </property>
        <property name="district" type="string">
            <column name="district" length="50" not-null="true" />
        </property>
        <property name="country" type="string">
            <column name="country" length="100" not-null="true" />
        </property>
        
        <one-to-one name="person" constrained="true" class="entity.common.Person"></one-to-one>
    </class>
</hibernate-mapping>
